{
    "haskell-nix": {
        "branch": "master",
        "description": "Alternative Haskell Infrastructure for Nixpkgs",
        "homepage": "https://input-output-hk.github.io/haskell.nix",
        "owner": "input-output-hk",
        "repo": "haskell.nix",
        "rev": "3856d2d24dca0ecc71fcfc314253a2a2d07a3c4f",
        "sha256": "0s69nasqhkv8n0qmdv075k83p3z584ja9vkzdnp2291mymghvx87",
        "type": "tarball",
        "url": "https://github.com/input-output-hk/haskell.nix/archive/3856d2d24dca0ecc71fcfc314253a2a2d07a3c4f.tar.gz",
        "url_template": "https://github.com/<owner>/<repo>/archive/<rev>.tar.gz"
    },
    "nixpkgs": {
        "branch": "nixpkgs-unstable",
        "description": "Nix Packages collection",
        "homepage": "https://github.com/NixOS/nixpkgs",
        "owner": "NixOS",
        "repo": "nixpkgs",
        "rev": "e85975942742a3728226ac22a3415f2355bfc897",
        "sha256": "0zg5c9if4dlk4f0w14439ixjv50m04yfxf0l3bmrhhsgq1f6yk0m",
        "type": "tarball",
        "url": "https://github.com/NixOS/nixpkgs/archive/e85975942742a3728226ac22a3415f2355bfc897.tar.gz",
        "url_template": "https://github.com/<owner>/<repo>/archive/<rev>.tar.gz"
    }
}
